yard/__init__.py
yard/api.py
yard/consts.py
yard/exceptions.py
yard/fields.py
yard/forms.py
yard/http.py
yard/metadata.py
yard/pagination.py
yard/tests.py
yard/utils.py
yard/version.py
yard/decorators/__init__.py
yard/decorators/django_alo_forms.py
yard/decorators/django_contrib_auth.py
yard/decorators/django_key_auth.py
yard/decorators/django_throttling.py
yard/decorators/utils.py
yard/resources/__init__.py
yard/resources/base.py
yard/resources/meta.py
yard/resources/mixins/__init__.py
yard/resources/mixins/collection.py
yard/resources/mixins/edit.py
yard/resources/mixins/element.py
yard/resources/mixins/new.py
yard/resources/mixins/options.py
yard/serializers/__init__.py
yard/serializers/base.py
yard/serializers/geojson.py
yard/serializers/hypermedia.py
yard/serializers/mobile.py
yard/serializers/uglification.py
yard/swagger/__init__.py
yard/swagger/consts.py
yard/swagger/functions.py
yard/swagger/urls.py
yard/swagger/view.py
yard/testcases/__init__.py
yard/testcases/api.py
yard/testcases/base.py
yard/testcases/metadata.py
yard/testcases/methods.py
yard/testcases/mobile.py
yard/testcases/pagination.py
yard/testcases/randomizer.py
yard/testcases/serializer.py
yard_framework-3.6.0.dist-info/DESCRIPTION.rst
yard_framework-3.6.0.dist-info/METADATA
yard_framework-3.6.0.dist-info/metadata.json
yard_framework-3.6.0.dist-info/RECORD
yard_framework-3.6.0.dist-info/top_level.txt
yard_framework-3.6.0.dist-info/WHEEL
