Metadata-Version: 2.0
Name: yard-framework
Version: 3.6.0
Summary: Yet Another Resftul Django framework
Home-page: https://github.com/laginha/yard/tree/develop
Author: Diogo Laginha
Author-email: diogo.laginha.machado@gmail.com
License: MIT
Platform: UNKNOWN
Classifier: License :: OSI Approved :: MIT License
Classifier: Programming Language :: Python :: 2
Classifier: Intended Audience :: Developers
Requires-Dist: Django
Requires-Dist: ujson
Requires-Dist: rstr
Requires-Dist: gpolyencode
Requires-Dist: django-easy-response
Requires-Dist: django-key-auth
Requires-Dist: django-alo-forms
Requires-Dist: throttling
